{
    "version": "0.5.51",
    "description": "Open-source database management tool",
    "homepage": "https://github.com/t8y2/dbx",
    "license": "MIT",
    "architecture": {
        "64bit": {
            "url": "https://github.com/t8y2/dbx/releases/download/v0.5.51/DBX_0.5.51_x64-setup.exe",
            "hash": "32b15f1c265d27ae90500e2c4bdc2f0735b4d80edbdbac24670fb87c5d922afd"
        }
    },
    "innosetup": false,
    "installer": {
        "args": [
            "/S",
            "/D=$dir"
        ]
    },
    "uninstaller": {
        "file": "uninstall.exe",
        "args": "/S"
    },
    "checkver": {
        "github": "https://github.com/t8y2/dbx"
    },
    "autoupdate": {
        "architecture": {
            "64bit": {
                "url": "https://github.com/t8y2/dbx/releases/download/v$version/DBX_$version_x64-setup.exe"
            }
        }
    }
}
